__init__.py
postgrelib.py
postgrelib-0.0.1.dist-info/LICENSE
postgrelib-0.0.1.dist-info/METADATA
postgrelib-0.0.1.dist-info/WHEEL
postgrelib-0.0.1.dist-info/top_level.txt
postgrelib-0.0.1.dist-info/RECORD
