Metadata-Version: 2.1
Name: postgrelib
Version: 0.0.1
Summary: A simple general purpose PostgreSQL library that removes the need for SQL and focuses and basic functionality.
Author-email: Jerry Wu <jerrbearis2cool@gmail.com>
Classifier: Programming Language :: Python :: 3
Classifier: License :: OSI Approved :: MIT License
Classifier: Operating System :: OS Independent
Requires-Python: >=3.8
License-File: LICENSE
